{"nodes": [{"id": "vcs_VCSBackend", "label": "VCSBackend struct", "file_type": "code", "source_file": "vcs.go", "source_location": "line 33", "source_url": null, "captured_at": null, "author": null, "contributor": null}, {"id": "vcs_GitBackend", "label": "GitBackend VCS", "file_type": "code", "source_file": "vcs.go", "source_location": "line 98", "source_url": null, "captured_at": null, "author": null, "contributor": null}, {"id": "vcs_SubversionBackend", "label": "SubversionBackend VCS", "file_type": "code", "source_file": "vcs.go", "source_location": "line 203", "source_url": null, "captured_at": null, "author": null, "contributor": null}, {"id": "vcs_GitsvnBackend", "label": "GitsvnBackend VCS", "file_type": "code", "source_file": "vcs.go", "source_location": "line 255", "source_url": null, "captured_at": null, "author": null, "contributor": null}, {"id": "vcs_MercurialBackend", "label": "MercurialBackend VCS", "file_type": "code", "source_file": "vcs.go", "source_location": "line 324", "source_url": null, "captured_at": null, "author": null, "contributor": null}, {"id": "vcs_DarcsBackend", "label": "DarcsBackend VCS", "file_type": "code", "source_file": "vcs.go", "source_location": "line 363", "source_url": null, "captured_at": null, "author": null, "contributor": null}, {"id": "vcs_PijulBackend", "label": "PijulBackend VCS", "file_type": "code", "source_file": "vcs.go", "source_location": "line 414", "source_url": null, "captured_at": null, "author": null, "contributor": null}, {"id": "vcs_FossilBackend", "label": "FossilBackend VCS", "file_type": "code", "source_file": "vcs.go", "source_location": "line 469", "source_url": null, "captured_at": null, "author": null, "contributor": null}, {"id": "vcs_BazaarBackend", "label": "BazaarBackend VCS", "file_type": "code", "source_file": "vcs.go", "source_location": "line 509", "source_url": null, "captured_at": null, "author": null, "contributor": null}, {"id": "vcs_vcsRegistry", "label": "vcsRegistry map", "file_type": "code", "source_file": "vcs.go", "source_location": "line 545", "source_url": null, "captured_at": null, "author": null, "contributor": null}], "edges": [{"source": "vcs_GitsvnBackend", "target": "vcs_GitBackend", "relation": "references", "confidence": "INFERRED", "confidence_score": 0.8, "source_file": "vcs.go", "source_location": "line 131", "weight": 0.8}], "hyperedges": [{"nodes": ["vcs_GitBackend", "vcs_SubversionBackend", "vcs_GitsvnBackend", "vcs_MercurialBackend", "vcs_DarcsBackend", "vcs_PijulBackend", "vcs_FossilBackend", "vcs_BazaarBackend"], "relation": "VCS backend registry entries", "confidence": "EXTRACTED", "confidence_score": 1.0, "source_file": "vcs.go"}]}